aioserve/__init__.py
aioserve/schemas/base_scope.py
aioserve/schemas/datastructures.py
aioserve/schemas/request.py
aioserve/schemas/response.py
aioserve/server/__init__.py
aioserve/server/app.py
aioserve/server/http.py
aioserve-0.1.0.dist-info/METADATA
aioserve-0.1.0.dist-info/WHEEL
aioserve-0.1.0.dist-info/RECORD
