Metadata-Version: 2.3
Name: aioserve
Version: 0.1.0
Summary: A simple ASGI based web framework for exposing HTTP and MCP tools
License: MIT
Author: Bemnet Aschalew
Author-email: bemnetaschalewwodaj@gmail.com
Requires-Python: >=3.13
Classifier: Programming Language :: Python :: 3
Classifier: License :: OSI Approved :: MIT License
Classifier: Operating System :: OS Independent
Classifier: Framework :: ASGI :: Server
Classifier: Topic :: Internet :: WWW/HTTP :: WSGI :: Application
Requires-Dist: starlette (>=0.47.3,<0.48.0)
Requires-Dist: uvicorn (>=0.35.0,<0.36.0)
Project-URL: Repository, https://github.com/BemnetAschalew/aioserve
